visualdata/__init__.py
visualdata/image/__init__.py
visualdata/image/classification/__init__.py
visualdata/image/classification/dataset.py
visualdata/image/classification/keras/__init__.py
visualdata/image/classification/keras/dataset.py
visualdata/image/classification/keras/tests.py
visualdata/image/detection/__init__.py
visualdata/image/shared/__init__.py
visualdata/image/shared/tools.py
visualdata/shared/__init__.py
visualdata/shared/commons.py
visualdata/shared/dataset.py
visualdata/shared/tools.py
visualdata-0.0.5.dist-info/METADATA
visualdata-0.0.5.dist-info/RECORD
visualdata-0.0.5.dist-info/WHEEL
visualdata-0.0.5.dist-info/top_level.txt
