Metadata-Version: 2.1
Name: visualdata
Version: 0.0.5
Summary: library to manage image data
Home-page: https://github.com/perceptance/visualdata-lib
Author: Jie Feng
Author-email: jiefengdev@gmail.com
License: UNKNOWN
Keywords: computer vision image
Platform: UNKNOWN
Provides-Extra: tf_gpu
Provides-Extra: tf
Requires-Dist: absl-py (==0.2.2)
Requires-Dist: astor (==0.6.2)
Requires-Dist: bleach (==1.5.0)
Requires-Dist: chardet (==3.0.4)
Requires-Dist: deepimage (==0.0.6)
Requires-Dist: gast (==0.2.0)
Requires-Dist: grpcio (==1.12.1)
Requires-Dist: h5py (==2.8.0)
Requires-Dist: html5lib (==0.9999999)
Requires-Dist: idna (==2.7)
Requires-Dist: Keras (==2.2.0)
Requires-Dist: Keras-Applications (==1.0.2)
Requires-Dist: Keras-Preprocessing (==1.0.1)
Requires-Dist: Markdown (==2.6.11)
Requires-Dist: numpy (==1.14.3)
Requires-Dist: opencv-python (==3.4.0.12)
Requires-Dist: Pillow (==5.1.0)
Requires-Dist: pkginfo (==1.4.2)
Requires-Dist: protobuf (==3.6.0)
Requires-Dist: PyYAML (==3.12)
Requires-Dist: requests (==2.19.1)
Requires-Dist: requests-toolbelt (==0.8.0)
Requires-Dist: scipy (==1.1.0)
Requires-Dist: six (==1.11.0)
Requires-Dist: termcolor (==1.1.0)
Requires-Dist: tqdm (==4.23.4)
Requires-Dist: twine (==1.11.0)
Requires-Dist: urllib3 (==1.23)
Requires-Dist: Werkzeug (==0.14.1)
Provides-Extra: tf
Requires-Dist: tensorflow (>=1.0.0); extra == 'tf'
Provides-Extra: tf_gpu
Requires-Dist: tensorflow-gpu (>=1.0.0); extra == 'tf_gpu'
